<?xml version = '1.0' encoding = 'UTF-8'?>
<Diagram class="oracle.dbtools.crest.swingui.logical.DPVLogical" name="Logical" id="A9CD51F3-08C1-EC97-2343-FCFBADEABA7B">
<createdBy>I566304</createdBy>
<modifiedBy>I566304</modifiedBy>
<createdTime>2023-05-06 02:20:43 UTC</createdTime>
<autoRoute>false</autoRoute>
<boxInbox>true</boxInbox>
<showLegend>false</showLegend>
<showLabels>true</showLabels>
<showRelAttributes>false</showRelAttributes>
<gridEnabled>false</gridEnabled>
<showGrid>false</showGrid>
<diagramColor>-1</diagramColor>
<display>false</display>
<notation>1</notation>
<objectViews>
<OView class="oracle.dbtools.crest.swingui.logical.TVEntity" oid="17B937AB-3C1D-C65B-2E9D-8DD9C9E66641" otype="Entity" vid="331407B6-AADC-9180-95D8-F0CF73CEB035">
<hideElementsInCurrentOnly>false</hideElementsInCurrentOnly>
<bounds x="726" y="296" width="144" height="68"/>
</OView>
<OView class="oracle.dbtools.crest.swingui.logical.TVEntity" oid="228550D1-7686-C0EB-5EB4-C3BDABE05CEC" otype="Entity" vid="EA2F8C34-CA74-5062-1F65-84F0B2DF2D2F">
<hideElementsInCurrentOnly>false</hideElementsInCurrentOnly>
<bounds x="708" y="19" width="170" height="141"/>
</OView>
<OView class="oracle.dbtools.crest.swingui.logical.TVEntity" oid="5F7CE1F5-09CF-31AE-687C-BF657BC23FF8" otype="Entity" vid="B00C4593-FD41-F0A4-1BA6-1FE2CF96F343">
<hideElementsInCurrentOnly>false</hideElementsInCurrentOnly>
<bounds x="974" y="275" width="157" height="49"/>
</OView>
<OView class="oracle.dbtools.crest.swingui.logical.TVEntity" oid="87F7B305-68BD-FD7C-9097-6D9BB7CD18FC" otype="Entity" vid="36CB54BC-90A3-53A2-218B-62ED2764933C">
<hideElementsInCurrentOnly>false</hideElementsInCurrentOnly>
<bounds x="383" y="24" width="170" height="110"/>
</OView>
<OView class="oracle.dbtools.crest.swingui.logical.TVEntity" oid="AFC79A38-00C6-3700-1DFB-6B04E41E5AFC" otype="Entity" vid="F89682C4-C3C0-37E9-58A3-2E51B9D6358F">
<hideElementsInCurrentOnly>false</hideElementsInCurrentOnly>
<bounds x="976" y="340" width="157" height="54"/>
</OView>
<OView class="oracle.dbtools.crest.swingui.logical.TVEntity" oid="DF78D3B6-3C4A-25C0-5658-8C94AC1BA5BE" otype="Entity" vid="D976F3BA-DF48-744E-83D7-2C7212BE394A">
<hideElementsInCurrentOnly>false</hideElementsInCurrentOnly>
<bounds x="16" y="32" width="194" height="110"/>
</OView>
</objectViews>
<connectors>
<Connector class="oracle.dbtools.crest.swingui.logical.TVRelation" oid="0F3AC326-C38F-FC09-CF60-1BDA14B04267" otype="Relation" vid_source="EA2F8C34-CA74-5062-1F65-84F0B2DF2D2F" vid_target="331407B6-AADC-9180-95D8-F0CF73CEB035">
<hideElementsInCurrentOnly>false</hideElementsInCurrentOnly>
<backgroundColor>-16777216</backgroundColor>
<lineWidth>1</lineWidth>
<sourceLabel class="oracle.dbtools.crest.model.design.Label">
<site>0</site>
<labelBounds x="798" y="204" width="39" height="30"/>
<noBackgroundColor>true</noBackgroundColor>
<noForegroundColor>true</noForegroundColor>
</sourceLabel>
<targetLabel class="oracle.dbtools.crest.model.design.Label">
<site>2</site>
<labelBounds x="798" y="244" width="72" height="30"/>
<noBackgroundColor>true</noBackgroundColor>
<noForegroundColor>true</noForegroundColor>
</targetLabel>
<points>
<point x="798" y="160"/>
<point x="798" y="296"/>
</points>
</Connector>
<Connector class="oracle.dbtools.crest.swingui.logical.TVRelation" oid="5FB21AA9-F7FA-D135-5CCA-46C24AF0760F" otype="Relation" vid_source="EA2F8C34-CA74-5062-1F65-84F0B2DF2D2F" vid_target="36CB54BC-90A3-53A2-218B-62ED2764933C">
<hideElementsInCurrentOnly>false</hideElementsInCurrentOnly>
<backgroundColor>-16777216</backgroundColor>
<lineWidth>1</lineWidth>
<sourceLabel class="oracle.dbtools.crest.model.design.Label">
<site>0</site>
<labelBounds x="655" y="49" width="47" height="30"/>
<noBackgroundColor>true</noBackgroundColor>
<noForegroundColor>true</noForegroundColor>
</sourceLabel>
<targetLabel class="oracle.dbtools.crest.model.design.Label">
<site>2</site>
<labelBounds x="563" y="82" width="91" height="30"/>
<noBackgroundColor>true</noBackgroundColor>
<noForegroundColor>true</noForegroundColor>
</targetLabel>
<points>
<point x="708" y="79"/>
<point x="553" y="79"/>
</points>
</Connector>
<Connector class="oracle.dbtools.crest.swingui.logical.TVRelation" oid="64AD8F40-1074-99CB-B0B3-F0F9EBDCEE52" otype="Relation" vid_source="F89682C4-C3C0-37E9-58A3-2E51B9D6358F" vid_target="331407B6-AADC-9180-95D8-F0CF73CEB035">
<hideElementsInCurrentOnly>false</hideElementsInCurrentOnly>
<backgroundColor>-16777216</backgroundColor>
<lineWidth>1</lineWidth>
<points>
<point x="976" y="352"/>
<point x="870" y="352"/>
</points>
</Connector>
<Connector class="oracle.dbtools.crest.swingui.logical.TVRelation" oid="7F0D59EE-23F4-993E-1EE5-70BB33CA74BA" otype="Relation" vid_source="D976F3BA-DF48-744E-83D7-2C7212BE394A" vid_target="36CB54BC-90A3-53A2-218B-62ED2764933C">
<hideElementsInCurrentOnly>false</hideElementsInCurrentOnly>
<backgroundColor>-16777216</backgroundColor>
<lineWidth>1</lineWidth>
<sourceLabel class="oracle.dbtools.crest.model.design.Label">
<site>0</site>
<labelBounds x="220" y="53" width="47" height="30"/>
<noBackgroundColor>true</noBackgroundColor>
<noForegroundColor>true</noForegroundColor>
</sourceLabel>
<targetLabel class="oracle.dbtools.crest.model.design.Label">
<site>2</site>
<labelBounds x="292" y="86" width="85" height="30"/>
<noBackgroundColor>true</noBackgroundColor>
<noForegroundColor>true</noForegroundColor>
</targetLabel>
<points>
<point x="210" y="83"/>
<point x="383" y="83"/>
</points>
</Connector>
<Connector class="oracle.dbtools.crest.swingui.logical.TVRelation" oid="9DC5107D-7E30-F524-8F92-AAE9CD6D94AD" otype="Relation" vid_source="331407B6-AADC-9180-95D8-F0CF73CEB035" vid_target="B00C4593-FD41-F0A4-1BA6-1FE2CF96F343">
<hideElementsInCurrentOnly>false</hideElementsInCurrentOnly>
<backgroundColor>-16777216</backgroundColor>
<lineWidth>1</lineWidth>
<points>
<point x="870" y="310"/>
<point x="974" y="310"/>
</points>
</Connector>
</connectors>
<arcs>
<Arc class="oracle.dbtools.crest.swingui.logical.TVArc" oid="1D802BBE-5789-0C88-C511-CBA9A3039964" otype="Arc" vid="A5920E1E-BF1D-4A13-EA76-6DB14D025933">
<hideElementsInCurrentOnly>false</hideElementsInCurrentOnly>
<bounds x="706" y="276" width="184" height="108"/>
</Arc>
</arcs>
</Diagram>