<?xml version = '1.0' encoding = 'UTF-8'?>
<Relation class="oracle.dbtools.crest.model.design.logical.Relation" name="Relation_2" directorySegmentName="seg_0" id="23E1F8BA-EC7A-1545-E8BF-838CA6A0B117">
<createdBy>I566304</createdBy>
<createdTime>2023-05-06 22:36:37 UTC</createdTime>
<ownerDesignName>LLOVERAS_EJ_11_DATAMODELER</ownerDesignName>
<engineerTo>
<item key="E1E9CDF1-2547-AB60-ABF8-11BA0A718AE9" value="true"/>
</engineerTo>
<sourcePk>328AAA65-CD03-9BF5-C4CD-F7EFB784C606</sourcePk>
<identifying>false</identifying>
<nameOnSource>llegan</nameOnSource>
<nameOnTarget>llega</nameOnTarget>
<optionalSource>true</optionalSource>
<optionalTarget>true</optionalTarget>
<sourceCardinality>1</sourceCardinality>
<sourceEntity>3101DE72-E23C-E2CF-EE5B-9CB1F500D05B</sourceEntity>
<targetCardinalityString>*</targetCardinalityString>
<targetEntity>D3210B8E-DDAF-298D-186B-2D68958066DF</targetEntity>
<transferable>true</transferable>
<deleteRule>NO ACTION</deleteRule>
</Relation>